{
  "id": "WorkflowFormUI/2.0/defs/ScreenType.json",
  "$schema": "http://json-schema.org/draft-04/schema#",
  "definitions": {
    "ScreenType": {
      "description": "Logical group of widgets for user convenience",
      "type": "object",
      "additionalProperties": false,
      "properties": {
        "title": {
          "type": "string",
          "maxLength": 256
        },
        "description": {
          "type": "string",
          "maxLength": 1024
        },
        "type": {
          "type": "string",
          "maxLength": 128
        },
        "properties": {
          "$ref": "WorkflowFormUI/2.0/defs/PropertiesType.json#/definitions/PropertiesType"
        },
        "header": {
          "type": "array",
          "items": {
            "$ref": "WorkflowFormUI/2.0/defs/WidgetType.json#/definitions/WidgetType"
          },
          "minItems": 1,
          "maxItems": 256,
          "additionalItems": false
        },
        "widgets": {
          "type": "array",
          "items": {
            "$ref": "WorkflowFormUI/2.0/defs/WidgetType.json#/definitions/WidgetType"
          },
          "minItems": 1,
          "maxItems": 256,
          "additionalItems": false
        },
        "footer": {
          "type": "array",
          "items": {
            "$ref": "WorkflowFormUI/2.0/defs/WidgetType.json#/definitions/WidgetType"
          },
          "minItems": 1,
          "maxItems": 256,
          "additionalItems": false
        }
      }
    }
  }
}
